[
  {
    "channel": "dyrdom1_катает",
    "id": 5681,
    "date": "2025-08-21T07:16:53+00:00",
    "text_preview": "Удалось даже назвать его руку до кола 🔥",
    "views": 2663,
    "forwards": 3,
    "replies": 8,
    "total_reactions": 2321,
    "engagement_count": 2332,
    "engagement_rate": 87.5704,
    "reactions_per_view": 0.871573
  },
  {
    "channel": "рывок_из_бедности",
    "id": 1856,
    "date": "2025-09-24T11:06:22+00:00",
    "text_preview": "Что могу сказать, в целом то - как я играл в двух-трех столах это было лучшей моей игрой за этот турнир думаю, то что я …",
    "views": 7692,
    "forwards": 38,
    "replies": 139,
    "total_reactions": 2431,
    "engagement_count": 2608,
    "engagement_rate": 33.9054,
    "reactions_per_view": 0.316043
  },
  {
    "channel": "poker_ability",
    "id": 4899,
    "date": "2025-08-19T14:10:11+00:00",
    "text_preview": "🔥**Розыгрыш призов на $1500+: деньги на карту, билеты на курсы, турнирные деньги и  кэш баксы на ПокерОк! **\n\nВ честь 10…",
    "views": 3168,
    "forwards": 44,
    "replies": 754,
    "total_reactions": 133,
    "engagement_count": 931,
    "engagement_rate": 29.3876,
    "reactions_per_view": 0.041982
  },
  {
    "channel": "poker_ability",
    "id": 5077,
    "date": "2025-11-17T14:07:20+00:00",
    "text_preview": "🎁**Розыгрыш 110 билетов на отборочные турниры EAPT Armenia на ПокерОК.**\n\nСкоро стартнет большая турнирная серия EAPT в …",
    "views": 956,
    "forwards": 7,
    "replies": 231,
    "total_reactions": 32,
    "engagement_count": 270,
    "engagement_rate": 28.2427,
    "reactions_per_view": 0.033473
  },
  {
    "channel": "покерные_хроники",
    "id": 2306,
    "date": "2025-10-11T11:50:48+00:00",
    "text_preview": "",
    "views": 3145,
    "forwards": 12,
    "replies": 691,
    "total_reactions": 40,
    "engagement_count": 743,
    "engagement_rate": 23.6248,
    "reactions_per_view": 0.012719
  }
]